shift_register.v
`timescale 1ns/1ps

module shift_register (
    input clk,
    input rst,
    input sin,
    output reg [3:0] q
);

always @(posedge clk or posedge rst) begin
    if (rst)
        q <= 4'b0000;
    else
        q <= {q[2:0], sin};
end

endmodule

tb.v
`timescale 1ns/1ps

module tb;

reg clk;
reg rst;
reg sin;
wire [3:0] q;

shift_register dut (
    .clk(clk),
    .rst(rst),
    .sin(sin),
    .q(q)
);

always #5 clk = ~clk;

initial begin
    $dumpfile("shift_register.vcd");
    $dumpvars(0,tb);

    clk = 0;
    rst = 1;
    sin = 0;

    #10 rst = 0;

    sin = 1; #10;
    sin = 0; #10;
    sin = 1; #10;
    sin = 1; #10;
    sin = 0; #10;
    sin = 1; #10;

    #20 $finish;
end

always @(posedge clk) begin
    $display("time=%0t sin=%b q=%b", $time, sin, q);
end

endmodule

shift_register.vcd
$version Generated by VerilatedVcd $end
$timescale 1ps $end
 $scope module tb $end
  $var wire 1 " clk $end
  $var wire 1 # rst $end
  $var wire 1 $ sin $end
  $var wire 4 % q [3:0] $end
  $scope module dut $end
   $var wire 1 " clk $end
   $var wire 1 # rst $end
   $var wire 1 $ sin $end
   $var wire 4 % q [3:0] $end
  $upscope $end
 $upscope $end
$enddefinitions $end


#0
0"
1#
0$
b0000 %
#5000
1"
#10000
0"
0#
1$
#15000
1"
b0001 %
#20000
0"
0$
#25000
1"
b0010 %
#30000
0"
1$
#35000
1"
b0101 %
#40000
0"
#45000
1"
b1011 %
#50000
0"
0$
#55000
1"
b0110 %
#60000
0"
1$
#65000
1"
b1101 %
#70000
0"
#75000
1"
b1011 %
#80000
0"
#85000
1"
b0111 %
